{
  "futures" : [
    {
      "caption" : "CSI 300 Index" , "value" : "IF",
      "columns" : [
        { "caption" : "January", "value" : "F" },
        { "caption" : "February", "value" : "G"},
        { "caption" : "March", "value" : "H" },
        { "caption" : "April", "value" : "J"},
        { "caption" : "May", "value" : "K" },
        { "caption" : "June", "value" : "M" },
        { "caption" : "July", "value" : "N" },
        { "caption" : "August", "value" : "Q" },
        { "caption" : "September", "value" : "U" },
        { "caption" : "October", "value" : "V"},
        { "caption" : "November", "value" : "X" },
        { "caption" : "December", "value" : "Z"}
      ]
    },{
      "caption" : "SSE 50 Index" , "value" : "IH",
      "columns" : [
        { "caption" : "January", "value" : "F" },
        { "caption" : "February", "value" : "G"},
        { "caption" : "March", "value" : "H" },
        { "caption" : "April", "value" : "J"},
        { "caption" : "May", "value" : "K" },
        { "caption" : "June", "value" : "M" },
        { "caption" : "July", "value" : "N" },
        { "caption" : "August", "value" : "Q" },
        { "caption" : "September", "value" : "U" },
        { "caption" : "October", "value" : "V"},
        { "caption" : "November", "value" : "X" },
        { "caption" : "December", "value" : "Z"}
      ]
    },{
      "caption" : "CSI 500 Index" , "value" : "IC",
      "columns" : [
        { "caption" : "January", "value" : "F" },
        { "caption" : "February", "value" : "G"},
        { "caption" : "March", "value" : "H" },
        { "caption" : "April", "value" : "J"},
        { "caption" : "May", "value" : "K" },
        { "caption" : "June", "value" : "M" },
        { "caption" : "July", "value" : "N" },
        { "caption" : "August", "value" : "Q" },
        { "caption" : "September", "value" : "U" },
        { "caption" : "October", "value" : "V"},
        { "caption" : "November", "value" : "X" },
        { "caption" : "December", "value" : "Z"}
      ]
    },{
      "caption" : "5-year Treasury Bond" , "value" : "TF",
      "columns" : [
        { "caption" : "March", "value" : "H" },
        { "caption" : "June", "value" : "M" },
        { "caption" : "September", "value" : "U" },
        { "caption" : "December", "value" : "Z"}
      ]
    },{
      "caption" : "10-year Treasury Bond" , "value" : "T",
      "columns" : [
        { "caption" : "March", "value" : "H" },
        { "caption" : "June", "value" : "M" },
        { "caption" : "September", "value" : "U" },        
        { "caption" : "December", "value" : "Z"}
      ]
    }
  ]
}
