{"items":[{"c":"Gross Profit Margin","v":"grossProfitMargin"},{"c":"EBIT Margin","v":"ebitMargin"},{"c":"EBITDA Margin","v":"ebitdaMargin"},{"c":"Operating Profit Margin","v":"operatingProfitMargin"},{"c":"Pretax Profit Margin","v":"pretaxProfitMargin"},{"c":"Continuous Operations Profit Margin","v":"continuousOperationsProfitMargin"},{"c":"Net Profit Margin","v":"netProfitMargin"},{"c":"Bottom Line Profit Margin","v":"bottomLineProfitMargin"},{"c":"Receivables Turnover","v":"receivablesTurnover"},{"c":"Payables Turnover","v":"payablesTurnover"},{"c":"Inventory Turnover","v":"inventoryTurnover"},{"c":"Fixed Asset Turnover","v":"fixedAssetTurnover"},{"c":"Asset Turnover","v":"assetTurnover"},{"c":"Current Ratio","v":"currentRatio"},{"c":"Quick Ratio","v":"quickRatio"},{"c":"Solvency Ratio","v":"solvencyRatio"},{"c":"Cash Ratio","v":"cashRatio"},{"c":"Price / Earnings Ratio","v":"priceToEarningsRatio"},{"c":"Price / Earnings Growth Ratio","v":"priceToEarningsGrowthRatio"},{"c":"Forward Price/ Earnings Growth Ratio","v":"forwardPriceToEarningsGrowthRatio"},{"c":"Price / Book Ratio","v":"priceToBookRatio"},{"c":"Price / Sales Ratio","v":"priceToSalesRatio"},{"c":"Price / Free Cash Flow Ratio","v":"priceToFreeCashFlowRatio"},{"c":"Price / Operating Cash Flow Ratio","v":"priceToOperatingCashFlowRatio"},{"c":"Debt / Assets Ratio","v":"debtToAssetsRatio"},{"c":"Debt / Equity Ratio","v":"debtToEquityRatio"},{"c":"Debt / Capital Ratio","v":"debtToCapitalRatio"},{"c":"Long Term Debt / Capital Ratio","v":"longTermDebtToCapitalRatio"},{"c":"Financial Leverage Ratio","v":"financialLeverageRatio"},{"c":"Working Capital Turnover Ratio","v":"workingCapitalTurnoverRatio"},{"c":"Operating Cash Flow Ratio","v":"operatingCashFlowRatio"},{"c":"Operating Cash Flow Sales Ratio","v":"operatingCashFlowSalesRatio"},{"c":"Free Cash Flow Operating Cash Flow Ratio","v":"freeCashFlowOperatingCashFlowRatio"},{"c":"Debt Service Coverage Ratio","v":"debtServiceCoverageRatio"},{"c":"Interest Coverage Ratio","v":"interestCoverageRatio"},{"c":"Short Term Operating Cash Flow Coverage Ratio","v":"shortTermOperatingCashFlowCoverageRatio"},{"c":"Operating Cash Flow Coverage Ratio","v":"operatingCashFlowCoverageRatio"},{"c":"Capital Expenditure Coverage Ratio","v":"capitalExpenditureCoverageRatio"},{"c":"Dividend Paid and Capex Coverage Ratio","v":"dividendPaidAndCapexCoverageRatio"},{"c":"Dividend Payout Ratio","v":"dividendPayoutRatio"},{"c":"Dividend Yield","v":"dividendYield"},{"c":"Dividend Yield Percentage","v":"dividendYieldPercentage"},{"c":"Revenue per Share","v":"revenuePerShare"},{"c":"Net Income per Share","v":"netIncomePerShare"},{"c":"Interest Debt per Share","v":"interestDebtPerShare"},{"c":"Cash per Share","v":"cashPerShare"},{"c":"Book Value per Share","v":"bookValuePerShare"},{"c":"Tangible Book Value per Share","v":"tangibleBookValuePerShare"},{"c":"Shareholders Equity per Share","v":"shareholdersEquityPerShare"},{"c":"Operating Cash Flow per Share","v":"operatingCashFlowPerShare"},{"c":"Capex per Share","v":"capexPerShare"},{"c":"Free Cash Flow per Share","v":"freeCashFlowPerShare"},{"c":"Net Income per EBT","v":"netIncomePerEBT"},{"c":"EBT per EBIT","v":"ebtPerEbit"},{"c":"Price / Fair Value","v":"priceToFairValue"},{"c":"Debt / Market Cap","v":"debtToMarketCap"},{"c":"Effective Tax Rate","v":"effectiveTaxRate"},{"c":"Enterprise Value Multiple","v":"enterpriseValueMultiple"}]}