{"items":[{"c":"Overall Index","v":"cpih1dim1A0"},{"c":"01 Food and non-alcoholic beverages","v":"cpih1dim1T10000"},{"c":"01.1 Food","v":"cpih1dim1G10100"},{"c":"01.1.1 Bread and cereals","v":"cpih1dim1S10101"},{"c":"01.1.2 Meat","v":"cpih1dim1S10102"},{"c":"01.1.3 Fish","v":"cpih1dim1S10103"},{"c":"01.1.4 Milk, cheese and eggs","v":"cpih1dim1S10104"},{"c":"01.1.5 Oils and fats","v":"cpih1dim1S10105"},{"c":"01.1.6 Fruit","v":"cpih1dim1S10106"},{"c":"01.1.7 Vegetables including potatoes and tubers","v":"cpih1dim1S10107"},{"c":"01.1.8 Sugar, jam, syrups, chocolate and confectionery","v":"cpih1dim1S10108"},{"c":"01.1.9 Food products (nec)","v":"cpih1dim1S10109"},{"c":"01.2 Non-alcoholic beverages","v":"cpih1dim1G10200"},{"c":"01.2.1 Coffee, tea and cocoa","v":"cpih1dim1S10201"},{"c":"01.2.2 Mineral waters, soft drinks and juices","v":"cpih1dim1S10202"},{"c":"02 Alcoholic beverages and tobacco","v":"cpih1dim1T20000"},{"c":"02.1 Alcoholic beverages","v":"cpih1dim1G20100"},{"c":"02.1.1 Spirits","v":"cpih1dim1S20101"},{"c":"02.1.2 Wine","v":"cpih1dim1S20102"},{"c":"02.1.3 Beer","v":"cpih1dim1S20103"},{"c":"02.2 Tobacco","v":"cpih1dim1G20200"},{"c":"02.2.0 Tobacco","v":"cpih1dim1S20200"},{"c":"03 Clothing and footwear","v":"cpih1dim1T30000"},{"c":"03.1 Clothing","v":"cpih1dim1G30100"},{"c":"03.1.2 Garments","v":"cpih1dim1S30102"},{"c":"03.1.3 Other clothing and clothing accessories","v":"cpih1dim1S30103"},{"c":"03.1.4 Cleaning, repair and hire of clothing","v":"cpih1dim1S30104"},{"c":"03.2 Footwear including repairs","v":"cpih1dim1G30200"},{"c":"03.2.0 Footwear including repairs","v":"cpih1dim1S30200"},{"c":"04 Housing, water, electricity, gas and other fuels","v":"cpih1dim1T40000"},{"c":"04.1 Actual rentals for housing","v":"cpih1dim1G40100"},{"c":"04.1.0 Actual rentals for housing","v":"cpih1dim1S40100"},{"c":"04.2.0 Owner Occupied Housing Costs","v":"cpih1dim1G40200"},{"c":"04.2.0 Owner Occupied Housing Costs","v":"cpih1dim1S40200"},{"c":"04.3 Regular maintenance and repair of the dwelling","v":"cpih1dim1G40300"},{"c":"04.3.1 Materials for maintenance and repair","v":"cpih1dim1S40301"},{"c":"04.3.2 Services for maintenance and repair","v":"cpih1dim1S40302"},{"c":"04.4 Water supply and misc. services for the dwelling","v":"cpih1dim1G40400"},{"c":"04.4.1 Water supply","v":"cpih1dim1S40401"},{"c":"04.4.3 Sewerage collection","v":"cpih1dim1S40403"},{"c":"04.5 Electricity , gas and other fuels","v":"cpih1dim1G40500"},{"c":"04.5.1 Electricity","v":"cpih1dim1S40501"},{"c":"04.5.2 Gas","v":"cpih1dim1S40502"},{"c":"04.5.3 Liquid fuels","v":"cpih1dim1S40503"},{"c":"04.5.4 Solid fuels","v":"cpih1dim1S40504"},{"c":"04.9.0 Council Tax and rates","v":"cpih1dim1G40900"},{"c":"04.9.0 Council Tax and rates","v":"cpih1dim1S40900"},{"c":"05 Furniture, household equipment and maintenance","v":"cpih1dim1T50000"},{"c":"05.1 Furniture, furnishings and carpets","v":"cpih1dim1G50100"},{"c":"05.1.1 Furniture and furnishings","v":"cpih1dim1S50101"},{"c":"05.1.2 Carpets and other floor coverings","v":"cpih1dim1S50102"},{"c":"05.2 Household textiles","v":"cpih1dim1G50200"},{"c":"05.2.0 Household Textiles","v":"cpih1dim1S50200"},{"c":"05.3 Household appliances, fitting and repairs","v":"cpih1dim1G50300"},{"c":"05.3.1/2 Major appliances and small electric goods","v":"cpih1dim1S50301"},{"c":"05.3.3 Repair of household appliances","v":"cpih1dim1S50303"},{"c":"05.4 Glassware, tableware and household utensils","v":"cpih1dim1G50400"},{"c":"05.4.0 Glassware, Tableware and Household Utensils","v":"cpih1dim1S50400"},{"c":"05.5 Tools and equipment for house and garden","v":"cpih1dim1G50500"},{"c":"05.5.0 Tools and equipment for House and Garden","v":"cpih1dim1S50500"},{"c":"05.6 Goods and services for routine maintenance","v":"cpih1dim1G50600"},{"c":"05.6.1 Non-durable household goods","v":"cpih1dim1S50601"},{"c":"05.6.2 Domestic services and household services","v":"cpih1dim1S50602"},{"c":"06 Health","v":"cpih1dim1T60000"},{"c":"06.1 Medical products, appliances and equipment","v":"cpih1dim1G60100"},{"c":"06.1.1 Pharmaceutical products","v":"cpih1dim1S60101"},{"c":"06.1.2/3 Other medical and therapeutic equipment","v":"cpih1dim1S60102"},{"c":"06.2 Out-patient services","v":"cpih1dim1G60200"},{"c":"06.2.1/3 Medical services, paramedical services","v":"cpih1dim1S60201"},{"c":"06.2.2 Dental services","v":"cpih1dim1S60202"},{"c":"06.3 Hospital services","v":"cpih1dim1G60300"},{"c":"06.3.0 Hospital Services","v":"cpih1dim1S60300"},{"c":"07 Transport","v":"cpih1dim1T70000"},{"c":"07.1 Purchase of vehicles","v":"cpih1dim1G70100"},{"c":"07.1.1 New Cars","v":"cpih1dim1S70181"},{"c":"07.1.1b Second Hand Cars","v":"cpih1dim1S70191"},{"c":"07.1.2/3 Motorcycles and bicycles","v":"cpih1dim1S70102"},{"c":"07.2 Operation of personal transport equipment","v":"cpih1dim1G70200"},{"c":"07.2.1 Spare parts and accessories","v":"cpih1dim1S70201"},{"c":"07.2.2 Fuels and lubricants","v":"cpih1dim1S70202"},{"c":"07.2.3 Maintenance and repairs","v":"cpih1dim1S70203"},{"c":"07.2.4 Other services","v":"cpih1dim1S70204"},{"c":"07.3 Transport services","v":"cpih1dim1G70300"},{"c":"07.3.1 Passenger transport by railway","v":"cpih1dim1S70301"},{"c":"07.3.2 Passenger transport by road","v":"cpih1dim1S70302"},{"c":"07.3.3 Passenger transport by air","v":"cpih1dim1S70303"},{"c":"07.3.4 Passenger transport by sea and inland waterway","v":"cpih1dim1S70304"},{"c":"08 Communication","v":"cpih1dim1T80000"},{"c":"08.1 Postal services","v":"cpih1dim1G80100"},{"c":"08.1.0 Postal Services","v":"cpih1dim1S80100"},{"c":"08.2.0 Telephone and Telefax Equipment & Services","v":"cpih1dim1S80200"},{"c":"08.2/3 Telephone and telefax equip","v":"cpih1dim1G80200"},{"c":"09 Recreation and culture","v":"cpih1dim1T90000"},{"c":"09.1 Audio-visual equipment and related products","v":"cpih1dim1G90100"},{"c":"09.1.1 Reception and reproduction of sound and pictures","v":"cpih1dim1S90101"},{"c":"09.1.2 Photographic, cinematographic and optical equipment","v":"cpih1dim1S90102"},{"c":"09.1.3 Data processing equipment","v":"cpih1dim1S90103"},{"c":"09.1.4 Recording media","v":"cpih1dim1S90104"},{"c":"09.1.5 Repair of audio-visual equipment , related products","v":"cpih1dim1S90105"},{"c":"09.2.1/2 Major durables for in/outdoor recreation","v":"cpih1dim1S90201"},{"c":"09.3 Other recreational items, gardens and pets","v":"cpih1dim1G90300"},{"c":"09.3.1 Games, toys and hobbies","v":"cpih1dim1S90301"},{"c":"09.3.2 Equipment for sport and open-air recreation","v":"cpih1dim1S90302"},{"c":"09.3.3 Gardens, plants and flowers","v":"cpih1dim1S90303"},{"c":"09.3.4/5 Pets, related products and services","v":"cpih1dim1S90304"},{"c":"09.4 Recreational and cultural services","v":"cpih1dim1G90400"},{"c":"09.4.1 Recreational and sporting services","v":"cpih1dim1S90401"},{"c":"09.4.2 Cultural services","v":"cpih1dim1S90402"},{"c":"09.5 Books, newspapers and stationery","v":"cpih1dim1G90500"},{"c":"09.5.1 Books","v":"cpih1dim1S90501"},{"c":"09.5.2 Newspapers and periodicals","v":"cpih1dim1S90502"},{"c":"09.5.3/4 Misc. printed matter, stationery, drawing materials","v":"cpih1dim1S90503"},{"c":"09.6 Package holidays","v":"cpih1dim1G90600"},{"c":"09.6.0 Package Holidays","v":"cpih1dim1S90600"},{"c":"10 Education","v":"cpih1dim1T100000"},{"c":"10.0 Education","v":"cpih1dim1G100000"},{"c":"10.0.0 Education","v":"cpih1dim1S100000"},{"c":"11 Restaurants and hotels","v":"cpih1dim1T110000"},{"c":"11.1 Catering services","v":"cpih1dim1G110100"},{"c":"11.1.1 Restaurants, cafes","v":"cpih1dim1S110101"},{"c":"11.1.2 Canteens","v":"cpih1dim1S110102"},{"c":"11.2 Accommodation services","v":"cpih1dim1G110200"},{"c":"11.2.0 Accommodation Services","v":"cpih1dim1S110200"},{"c":"12 Miscellaneous goods and services","v":"cpih1dim1T120000"},{"c":"12.1 Personal care","v":"cpih1dim1G120100"},{"c":"12.1.1 Hairdressing and personal grooming establishments","v":"cpih1dim1S120101"},{"c":"12.1.2/3 Appliances and products for personal care","v":"cpih1dim1S120102"},{"c":"12.3 Personal effects (nec)","v":"cpih1dim1G120300"},{"c":"12.3.1 Jewellery, clocks and watches","v":"cpih1dim1S120301"},{"c":"12.3.2 Other personal effects","v":"cpih1dim1S120302"},{"c":"12.4 Social protection","v":"cpih1dim1G120400"},{"c":"12.4.0 Social Protection","v":"cpih1dim1S120400"},{"c":"12.5 Insurance","v":"cpih1dim1G120500"},{"c":"12.5.2 House contents insurance","v":"cpih1dim1S120502"},{"c":"12.5.3 Health insurance","v":"cpih1dim1S120503"},{"c":"12.5.4 Transport insurance","v":"cpih1dim1S120504"},{"c":"12.6 Financial services (nec)","v":"cpih1dim1G120600"},{"c":"12.6.2 Other financial services (nec)","v":"cpih1dim1S120602"},{"c":"12.7 Other services (nec)","v":"cpih1dim1G120700"},{"c":"12.7.0 Other Services Not Elsewhere covered","v":"cpih1dim1S120700"},{"c":"9.2 Other major durables for recreation and culture","v":"cpih1dim1G90200"}]}