 {
  "countries" :  [
    { "value" : "AT", "caption" : "Austria" },
    { "value" : "BE", "caption" : "Belgium" },
    { "value" : "BG", "caption" : "Bulgaria" },
    { "value" : "CY", "caption" : "Cyprus" },
    { "value" : "CZ", "caption" : "Czech Republic" },
    { "value" : "DE", "caption" : "Germany" },
    { "value" : "DK", "caption" : "Denmark" },
    { "value" : "EE", "caption" : "Estonia" },
    { "value" : "EL", "caption" : "Greece" },
    { "value" : "ES", "caption" : "Spain" },
    { "value" : "FI", "caption" : "Finland" },
    { "value" : "FR", "caption" : "France" },
    { "value" : "HR", "caption" : "Croatia" },
    { "value" : "HU", "caption" : "Hungary" },
    { "value" : "IE", "caption" : "Ireland" },
    { "value" : "IS", "caption" : "Iceland" },
    { "value" : "IT", "caption" : "Italy" },
    { "value" : "JP", "caption" : "Japan" },
    { "value" : "LT", "caption" : "Lithuania" },
    { "value" : "LU", "caption" : "Luxembourg" },
    { "value" : "LV", "caption" : "Latvia" },
    { "value" : "MT", "caption" : "Malta" },
    { "value" : "NL", "caption" : "Netherlands" },
    { "value" : "NO", "caption" : "Norway" },
    { "value" : "PL", "caption" : "Poland" },
    { "value" : "PT", "caption" : "Portugal" },
    { "value" : "RO", "caption" : "Romania" },
    { "value" : "SE", "caption" : "Sweden" },
    { "value" : "SI", "caption" : "Slovenia" },
    { "value" : "SK", "caption" : "Slovakia" },
    { "value" : "UK", "caption" : "United Kingdom" },
    { "value" : "US", "caption" : "United States" },
    { "value" : "TR", "caption" : "Turkey" }
   ]
}
