{"items":[{"c":"U.S. city average","v":"0000"},{"c":"Northeast urban","v":"0100"},{"c":"New England","v":"0110"},{"c":"Middle Atlantic","v":"0120"},{"c":"Midwest urban","v":"0200"},{"c":"East North Central","v":"0230"},{"c":"West North Central","v":"0240"},{"c":"South urban","v":"0300"},{"c":"South Atlantic","v":"0350"},{"c":"East South Central","v":"0360"},{"c":"West South Central","v":"0370"},{"c":"West urban","v":"0400"},{"c":"Mountain","v":"0480"},{"c":"Pacific","v":"0490"},{"c":"Boston-Cambridge-Newton, MA-NH","v":"S11A"},{"c":"New York-Newark-Jersey City, NY-NJ-PA","v":"S12A"},{"c":"Philadelphia-Camden-Wilmington, PA-NJ-DE-MD","v":"S12B"},{"c":"Chicago-Naperville-Elgin, IL-IN-WI","v":"S23A"},{"c":"Detroit-Warren-Dearborn, MI","v":"S23B"},{"c":"Minneapolis-St.Paul-Bloomington, MN-WI","v":"S24A"},{"c":"St. Louis, MO-IL","v":"S24B"},{"c":"Washington-Arlington-Alexandria, DC-VA-MD-WV","v":"S35A"},{"c":"Miami-Fort Lauderdale-West Palm Beach, FL","v":"S35B"},{"c":"Atlanta-Sandy Springs-Roswell, GA","v":"S35C"},{"c":"Tampa-St. Petersburg-Clearwater, FL","v":"S35D"},{"c":"Baltimore-Columbia-Towson, MD","v":"S35E"},{"c":"Dallas-Fort Worth-Arlington, TX","v":"S37A"},{"c":"Houston-The Woodlands-Sugar Land, TX","v":"S37B"},{"c":"Phoenix-Mesa-Scottsdale, AZ","v":"S48A"},{"c":"Denver-Aurora-Lakewood, CO","v":"S48B"},{"c":"Los Angeles-Long Beach-Anaheim, CA","v":"S49A"},{"c":"San Francisco-Oakland-Hayward, CA","v":"S49B"},{"c":"Riverside-San Bernardino-Ontario, CA","v":"S49C"},{"c":"Seattle-Tacoma-Bellevue, WA","v":"S49D"},{"c":"San Diego-Carlsbad, CA","v":"S49E"},{"c":"Urban Hawaii","v":"S49F"},{"c":"Urban Alaska","v":"S49G"}]}