{"prefix":"M.U2.","items":[{"c":"HICP - Overall index, ARC, NSA","v":"N.000000.4.ANR"},{"c":"HICP - Overall index, NSA","v":"N.000000.4.INX"},{"c":"HICP - Overall index, SA-WDA","v":"Y.000000.3.INX"},{"c":"HICP - All-items excluding energy, ARC, NSA","v":"N.XE0000.4.ANR"},{"c":"HICP - All-items excluding energy, NSA","v":"N.XE0000.3.INX"},{"c":"HICP - All-items excluding energy, SA-WDA","v":"Y.XE0000.3.INX"},{"c":"HICP - All-items excluding energy and food, ARC, NSA","v":"N.XEF000.4.ANR"},{"c":"HICP - All-items excluding energy and food, NSA","v":"N.XEF000.3.INX"},{"c":"HICP - All-items excluding energy and food, SA-WDA","v":"Y.XEF000.3.INX"},{"c":"HICP - Food, beverage, ARC, NSA (weight 15.7%)","v":"N.010000.4.ANR"},{"c":"HICP - Clothing, footwear, ARC, NSA (weight 5%)","v":"N.030000.4.ANR"},{"c":"HICP - Housing, electricity, ARC, NSA (weight 14.7%)","v":"N.040000.4.ANR"},{"c":"HICP - Household equipment, ARC, NSA (weight 6.4%)","v":"N.050000.4.ANR"},{"c":"HICP - Health, ARC, NSA (weight 5%)","v":"N.060000.4.ANR"},{"c":"HICP - Transport, ARC, NSA (weight 15.3%)","v":"N.070000.4.ANR"},{"c":"HICP - Communication, ARC, NSA (weight 2.7%)","v":"N.080000.4.ANR"},{"c":"HICP - Recreation, culture, ARC, NSA (weight 9.1%)","v":"N.090000.4.ANR"},{"c":"HICP - Education, ARC, NSA (weight 1%)","v":"N.100000.4.ANR"},{"c":"HICP - Restaurants, hotels, ARC, NSA (weight 11.2%)","v":"N.110000.4.ANR"},{"c":"HICP - Miscellaneous, ARC, NSA (weight 10%)","v":"N.120000.4.ANR"}]}